pollination/annual_irradiance/__init__.py
pollination/annual_irradiance/_postprocess.py
pollination/annual_irradiance/_prepare_folder.py
pollination/annual_irradiance/_raytracing.py
pollination/annual_irradiance/entry.py
pollination_annual_irradiance-0.4.3.dist-info/LICENSE
pollination_annual_irradiance-0.4.3.dist-info/METADATA
pollination_annual_irradiance-0.4.3.dist-info/WHEEL
pollination_annual_irradiance-0.4.3.dist-info/top_level.txt
pollination_annual_irradiance-0.4.3.dist-info/RECORD
